README
setup.py
bin/plumbca-server
plumbca/__init__.py
plumbca/backend.py
plumbca/cache.py
plumbca/collection.py
plumbca/config.py
plumbca/constants.py
plumbca/exceptions.py
plumbca/helpers.py
plumbca/log.py
plumbca/message.py
plumbca/protocol.py
plumbca/server.py
plumbca/worker.py
plumbca.egg-info/PKG-INFO
plumbca.egg-info/SOURCES.txt
plumbca.egg-info/dependency_links.txt
plumbca.egg-info/requires.txt
plumbca.egg-info/top_level.txt