Metadata-Version: 1.1
Name: plumbca
Version: 0.3.4
Summary: A lightweigth k/v database for caching and computing the frequently accessed data base on Redis.
Home-page: UNKNOWN
Author: Jason Lai
Author-email: jasonlai256@gmail.com
License: BSD
Platform: UNKNOWN
Classifier: Development Status :: 4 - Beta
Classifier: Intended Audience :: Developers
Classifier: Programming Language :: Python :: 3 :: Only
Classifier: Programming Language :: Python :: 3.3
Classifier: Programming Language :: Python :: 3.4
Classifier: Programming Language :: Python :: 3.5
